Metadata-Version: 2.1
Name: business-rules-enhanced
Version: 1.4.7
Summary: Fork of Venmo-Business-Rules: Python DSL for setting up business intelligence rules that can be configured without code  History -------  1.0.1 +++++ released 2016-3-16  - Fixes a packaging bug preventing 1.0.0 from being installed on some platforms.  1.0.0 +++++ released 2016-3-16  - Removes caching layer on rule decorator 
Home-page: https://github.com/cdisc-org/business-rules
Author: cdisc-org
Author-email: UNKNOWN
License: MIT
Platform: UNKNOWN
